datastructclass/__init__.py
datastructclass/datastructclass.py
datastructclass/py.typed
datastructclass-0.1.1.dist-info/LICENSE
datastructclass-0.1.1.dist-info/WHEEL
datastructclass-0.1.1.dist-info/METADATA
datastructclass-0.1.1.dist-info/RECORD
