Metadata-Version: 2.3
Name: datastructclass
Version: 0.1.1
Summary: datastructclass.
Keywords: dataclass,serialization,struct
Author-email: Alexander Bessman <alexander.bessman@gmail.com>
Requires-Python: >=3.9
Classifier: Programming Language :: Python :: 3
Classifier: Programming Language :: Python :: 3.9
Classifier: Programming Language :: Python :: 3.10
Classifier: Programming Language :: Python :: 3.11
Classifier: Programming Language :: Python :: 3.12
Classifier: Programming Language :: Python :: 3.13
Classifier: Development Status :: 4 - Beta
Classifier: License :: OSI Approved :: MIT License
Requires-Dist: black ; extra == "dev"
Requires-Dist: isort ; extra == "dev"
Requires-Dist: mypy ; extra == "dev"
Requires-Dist: ruff ; extra == "dev"
Requires-Dist: tox ; extra == "dev"
Requires-Dist: pytest ; extra == "test"
Requires-Dist: coverage ; extra == "test"
Project-URL: Home, https://github.com/bessman/datastructclass/
Provides-Extra: dev
Provides-Extra: test
